{
  "product": "Microsoft Purview",
  "id_level_1": 3.3,
  "id_level_2": "3.3.1",
  "title": "Ensure Information Protection sensitivity label policies are published",
  "profile": "E3 E5",
  "level": "L1",
  "status": "Manual",
  "description": "Publishes sensitivity label policies to classify and protect documents and emails.",
  "expected_value": "TRUE",
  "comparison": "equals",
  "evaluation_path": "purview.sensitivityLabelPoliciesPublished",
  "remediation": "Publish sensitivity label policies in Purview compliance portal.",
  "risk": "High",
  "impact": "",
  "likelihood": "",
  "risk_level": "",
  "tags": [
    "SensitivityLabels",
    "DataProtection"
  ]
}
